LICENSE
MANIFEST.in
README.md
setup.cfg
setup.py
pykush/__init__.py
pykush/pykush.py
yepkit_pykush.egg-info/PKG-INFO
yepkit_pykush.egg-info/SOURCES.txt
yepkit_pykush.egg-info/dependency_links.txt
yepkit_pykush.egg-info/entry_points.txt
yepkit_pykush.egg-info/requires.txt
yepkit_pykush.egg-info/top_level.txt