Metadata-Version: 2.1
Name: yepkit-pykush
Version: 0.3.5
Summary: Yepkit YKUSH Python API and command line tool
Home-page: https://github.com/yepkit/pykush
Author: ckuesters
Author-email: ckuesters@yepkit.com
License: MIT
Keywords: yepkit,ykush,pykush
Platform: UNKNOWN
Classifier: Development Status :: 3 - Alpha
Classifier: License :: OSI Approved :: MIT License
Classifier: Environment :: Console
Classifier: Intended Audience :: Developers
Classifier: Operating System :: POSIX :: Linux
Classifier: Operating System :: Microsoft :: Windows
Classifier: Operating System :: MacOS :: MacOS X
Classifier: Programming Language :: Python :: 2.7
Classifier: Programming Language :: Python :: 3.4
Classifier: Topic :: Utilities
Classifier: Topic :: System :: Hardware :: Hardware Drivers
